pkgcraft-0.0.11.dist-info/WHEEL
pkgcraft-0.0.11.dist-info/entry_points.txt
pkgcraft-0.0.11.dist-info/top_level.txt
pkgcraft-0.0.11.dist-info/RECORD
pkgcraft-0.0.11.dist-info/METADATA
pkgcraft.libs/libpkgcraft-4aa59e2c.so.0.0.16
pkgcraft/logging.cpython-312-aarch64-linux-gnu.so
pkgcraft/error.cpython-312-aarch64-linux-gnu.so
pkgcraft/restrict.cpython-312-aarch64-linux-gnu.so
pkgcraft/_pytest.py
pkgcraft/config.cpython-312-aarch64-linux-gnu.so
pkgcraft/__version__.py
pkgcraft/parse.cpython-312-aarch64-linux-gnu.so
pkgcraft/eapi.cpython-312-aarch64-linux-gnu.so
pkgcraft/_misc.cpython-312-aarch64-linux-gnu.so
pkgcraft/__init__.py
pkgcraft/types/ordered.cpython-312-aarch64-linux-gnu.so
pkgcraft/types/LICENSE
pkgcraft/types/__init__.py
pkgcraft/dep/use_dep.cpython-312-aarch64-linux-gnu.so
pkgcraft/dep/pkg.cpython-312-aarch64-linux-gnu.so
pkgcraft/dep/version.cpython-312-aarch64-linux-gnu.so
pkgcraft/dep/base.cpython-312-aarch64-linux-gnu.so
pkgcraft/dep/cpn.cpython-312-aarch64-linux-gnu.so
pkgcraft/dep/cpv.cpython-312-aarch64-linux-gnu.so
pkgcraft/dep/uri.cpython-312-aarch64-linux-gnu.so
pkgcraft/dep/__init__.py
pkgcraft/repo/base.cpython-312-aarch64-linux-gnu.so
pkgcraft/repo/ebuild.cpython-312-aarch64-linux-gnu.so
pkgcraft/repo/fake.cpython-312-aarch64-linux-gnu.so
pkgcraft/repo/set.cpython-312-aarch64-linux-gnu.so
pkgcraft/repo/__init__.py
pkgcraft/pkg/base.cpython-312-aarch64-linux-gnu.so
pkgcraft/pkg/fake.cpython-312-aarch64-linux-gnu.so
pkgcraft/pkg/__init__.py
pkgcraft/pkg/ebuild/keyword.cpython-312-aarch64-linux-gnu.so
pkgcraft/pkg/ebuild/xml.cpython-312-aarch64-linux-gnu.so
pkgcraft/pkg/ebuild/base.cpython-312-aarch64-linux-gnu.so
pkgcraft/pkg/ebuild/__init__.py
