Metadata-Version: 2.1
Name: pkgcraft
Version: 0.0.11
Summary: python bindings for pkgcraft
Author-email: Tim Harder <radhermit@gmail.com>
License: MIT
Project-URL: homepage, https://github.com/pkgcraft/pkgcraft-python
Keywords: gentoo,cython
Classifier: Intended Audience :: Developers
Classifier: Programming Language :: Python :: 3.11
Classifier: Programming Language :: Python :: 3.12
Requires-Python: >=3.11
Provides-Extra: test
Requires-Dist: pytest; extra == "test"
